splicer/__init__.py
splicer/cli.py
splicer_cli-1.0.7.dist-info/LICENSE
splicer_cli-1.0.7.dist-info/METADATA
splicer_cli-1.0.7.dist-info/WHEEL
splicer_cli-1.0.7.dist-info/entry_points.txt
splicer_cli-1.0.7.dist-info/top_level.txt
splicer_cli-1.0.7.dist-info/RECORD
