Metadata-Version: 2.1
Name: splicer-cli
Version: 1.0.7
Summary: A utility to copy audio files from a Splice folder to a final directory's staging directory.
Home-page: https://github.com/ajrpeggio/splicer
Author: AJ Rasmussen
Author-email: ajrpeggio@gmail.com
Classifier: Programming Language :: Python :: 3
Classifier: License :: OSI Approved :: MIT License
Classifier: Operating System :: OS Independent
Requires-Python: >=3.8
License-File: LICENSE
